l3ns/__init__.py
l3ns/defaults.py
l3ns/base/__init__.py
l3ns/base/network.py
l3ns/base/node.py
l3ns/base/subnet.py
l3ns/cluster/__init__.py
l3ns/cluster/node.py
l3ns/cluster/subnet.py
l3ns/cluster/utils.py
l3ns/debug/__init__.py
l3ns/debug/node.py
l3ns/debug/subnet.py
l3ns/ldc/__init__.py
l3ns/ldc/node.py
l3ns/ldc/subnet.py
l3ns/ldc/utils.py
l3ns/overlays/__init__.py
l3ns/overlays/base.py
l3ns/overlays/ospf.py
l3ns/overlays/rip.py
l3ns/swarm/__init__.py
l3ns/swarm/node.py
l3ns/swarm/subnet.py
l3ns/swarm/utils.py
l3ns/utils/__init__.py
l3ns/utils/args.py
l3ns/utils/docker_shortcuts.py
l3ns-0.0.1.dist-info/LICENSE
l3ns-0.0.1.dist-info/METADATA
l3ns-0.0.1.dist-info/WHEEL
l3ns-0.0.1.dist-info/top_level.txt
l3ns-0.0.1.dist-info/RECORD
