Metadata-Version: 2.1
Name: l3ns
Version: 0.0.1
Summary: L3 Network Simulator
Home-page: https://github.com/rukmarr/l3ns
Author: Daniil Malevanniy
Author-email: rukmarr@gmail.com
License: MIT
Platform: UNKNOWN
Classifier: Programming Language :: Python :: 3
Classifier: License :: OSI Approved :: MIT License
Classifier: Operating System :: POSIX :: Linux
Requires-Dist: docker
Requires-Dist: hashids
